redis_sentinel_connector/__init__.py
redis_sentinel_connector/redis_connector.py
redis_sentinel_connector-0.1.7.dist-info/LICENSE.txt
redis_sentinel_connector-0.1.7.dist-info/METADATA
redis_sentinel_connector-0.1.7.dist-info/WHEEL
redis_sentinel_connector-0.1.7.dist-info/top_level.txt
redis_sentinel_connector-0.1.7.dist-info/RECORD
