Metadata-Version: 2.1
Name: redis_sentinel_connector
Version: 0.1.7
Summary: A package that works with Redis Sentinel.
Home-page: https://github.com/ronaldodduarte/redis_sentinel_connector
Author: Ronaldo Duarte
Author-email: ronaldoduarte@globo.com
License: GNU
Classifier: Programming Language :: Python :: 3
Classifier: License :: OSI Approved :: GNU Lesser General Public License v3 (LGPLv3)
Classifier: Operating System :: OS Independent
Requires-Python: >=3.6
License-File: LICENSE.txt
Requires-Dist: redis ==5.0.6
Requires-Dist: fakeredis ==2.23.2
